nysecalendar/__init__.py
nysecalendar/nysecalendar.py
NYSECalendar-0.0.4.dist-info/LICENSE
NYSECalendar-0.0.4.dist-info/METADATA
NYSECalendar-0.0.4.dist-info/WHEEL
NYSECalendar-0.0.4.dist-info/top_level.txt
NYSECalendar-0.0.4.dist-info/RECORD
