Metadata-Version: 2.1
Name: NYSECalendar
Version: 0.0.4
Summary: NYSE Calendar
Author-email: Masa Nakamura <masayang.mobile@gmail.com>
License: Copyright (c) 2018 The Python Packaging Authority        
Project-URL: Homepage, https://github.com/masayang/nysecalendar
Project-URL: Bug Tracker, https://github.com/masayang/nysecalendar/issues
Classifier: Programming Language :: Python :: 3
Classifier: License :: OSI Approved :: MIT License
Classifier: Operating System :: OS Independent
Requires-Python: >=3.7
License-File: LICENSE
Requires-Dist: python-dateutil
